[
  {
    "stadiumId": "stadium_boston_college",
    "schoolId": "school_boston_college",
    "stadiumName": "Boston College Stadium",
    "city": "Chestnut Hill",
    "state": "MA",
    "capacity": 73513,
    "currentCapacity": 73513,
    "targetCapacity": 73513,
    "yearBuilt": 1945,
    "lastRenovation": 2025,
    "fieldType": "Artificial Turf",
    "surfaceQuality": 68,
    "fanExperience": 71,
    "homeFieldAdvantage": 84,
    "noiseRating": 69,
    "clubSeats": 5759,
    "suites": 1394
  },
  {
    "stadiumId": "stadium_california",
    "schoolId": "school_california",
    "stadiumName": "California Stadium",
    "city": "Berkeley",
    "state": "CA",
    "capacity": 67095,
    "currentCapacity": 67095,
    "targetCapacity": 67095,
    "yearBuilt": 1957,
    "lastRenovation": 2025,
    "fieldType": "Artificial Turf",
    "surfaceQuality": 56,
    "fanExperience": 61,
    "homeFieldAdvantage": 78,
    "noiseRating": 73,
    "clubSeats": 3177,
    "suites": 442
  },
  {
    "stadiumId": "stadium_clemson",
    "schoolId": "school_clemson",
    "stadiumName": "Clemson Stadium",
    "city": "Clemson",
    "state": "SC",
    "capacity": 71953,
    "currentCapacity": 71953,
    "targetCapacity": 71953,
    "yearBuilt": 2001,
    "lastRenovation": 2022,
    "fieldType": "Natural Grass",
    "surfaceQuality": 99,
    "fanExperience": 82,
    "homeFieldAdvantage": 70,
    "noiseRating": 93,
    "clubSeats": 2297,
    "suites": 813
  },
  {
    "stadiumId": "stadium_duke",
    "schoolId": "school_duke",
    "stadiumName": "Duke Stadium",
    "city": "Durham",
    "state": "NC",
    "capacity": 75259,
    "currentCapacity": 75259,
    "targetCapacity": 75259,
    "yearBuilt": 1948,
    "lastRenovation": 2009,
    "fieldType": "Artificial Turf",
    "surfaceQuality": 65,
    "fanExperience": 64,
    "homeFieldAdvantage": 75,
    "noiseRating": 74,
    "clubSeats": 5834,
    "suites": 1011
  },
  {
    "stadiumId": "stadium_florida_state",
    "schoolId": "school_florida_state",
    "stadiumName": "Florida State Stadium",
    "city": "Tallahassee",
    "state": "FL",
    "capacity": 68917,
    "currentCapacity": 68917,
    "targetCapacity": 68917,
    "yearBuilt": 2012,
    "lastRenovation": 2013,
    "fieldType": "Natural Grass",
    "surfaceQuality": 96,
    "fanExperience": 83,
    "homeFieldAdvantage": 89,
    "noiseRating": 71,
    "clubSeats": 4166,
    "suites": 618
  },
  {
    "stadiumId": "stadium_georgia_tech",
    "schoolId": "school_georgia_tech",
    "stadiumName": "Georgia Tech Stadium",
    "city": "Atlanta",
    "state": "GA",
    "capacity": 64134,
    "currentCapacity": 64134,
    "targetCapacity": 64134,
    "yearBuilt": 2013,
    "lastRenovation": 2020,
    "fieldType": "Natural Grass",
    "surfaceQuality": 75,
    "fanExperience": 61,
    "homeFieldAdvantage": 75,
    "noiseRating": 77,
    "clubSeats": 5567,
    "suites": 532
  },
  {
    "stadiumId": "stadium_louisville",
    "schoolId": "school_louisville",
    "stadiumName": "Louisville Stadium",
    "city": "Louisville",
    "state": "KY",
    "capacity": 89907,
    "currentCapacity": 89907,
    "targetCapacity": 89907,
    "yearBuilt": 1990,
    "lastRenovation": 2012,
    "fieldType": "Natural Grass",
    "surfaceQuality": 87,
    "fanExperience": 99,
    "homeFieldAdvantage": 87,
    "noiseRating": 91,
    "clubSeats": 2866,
    "suites": 1043
  },
  {
    "stadiumId": "stadium_miami_fl",
    "schoolId": "school_miami_fl",
    "stadiumName": "Miami (FL) Stadium",
    "city": "Miami Gardens",
    "state": "FL",
    "capacity": 85105,
    "currentCapacity": 85105,
    "targetCapacity": 85105,
    "yearBuilt": 1965,
    "lastRenovation": 2018,
    "fieldType": "Artificial Turf",
    "surfaceQuality": 70,
    "fanExperience": 90,
    "homeFieldAdvantage": 70,
    "noiseRating": 53,
    "clubSeats": 3055,
    "suites": 1110
  },
  {
    "stadiumId": "stadium_nc_state",
    "schoolId": "school_nc_state",
    "stadiumName": "NC State Stadium",
    "city": "Raleigh",
    "state": "NC",
    "capacity": 92652,
    "currentCapacity": 92652,
    "targetCapacity": 92652,
    "yearBuilt": 1941,
    "lastRenovation": 2018,
    "fieldType": "Artificial Turf",
    "surfaceQuality": 61,
    "fanExperience": 46,
    "homeFieldAdvantage": 73,
    "noiseRating": 76,
    "clubSeats": 2791,
    "suites": 1186
  },
  {
    "stadiumId": "stadium_north_carolina",
    "schoolId": "school_north_carolina",
    "stadiumName": "North Carolina Stadium",
    "city": "Chapel Hill",
    "state": "NC",
    "capacity": 88140,
    "currentCapacity": 88140,
    "targetCapacity": 88140,
    "yearBuilt": 1926,
    "lastRenovation": 2023,
    "fieldType": "Artificial Turf",
    "surfaceQuality": 57,
    "fanExperience": 77,
    "homeFieldAdvantage": 94,
    "noiseRating": 99,
    "clubSeats": 3067,
    "suites": 768
  },
  {
    "stadiumId": "stadium_pittsburgh",
    "schoolId": "school_pittsburgh",
    "stadiumName": "Pittsburgh Stadium",
    "city": "Pittsburgh",
    "state": "PA",
    "capacity": 80441,
    "currentCapacity": 80441,
    "targetCapacity": 80441,
    "yearBuilt": 2005,
    "lastRenovation": 2025,
    "fieldType": "Artificial Turf",
    "surfaceQuality": 84,
    "fanExperience": 47,
    "homeFieldAdvantage": 81,
    "noiseRating": 76,
    "clubSeats": 5411,
    "suites": 1307
  },
  {
    "stadiumId": "stadium_smu",
    "schoolId": "school_smu",
    "stadiumName": "SMU Stadium",
    "city": "Dallas",
    "state": "TX",
    "capacity": 87155,
    "currentCapacity": 87155,
    "targetCapacity": 87155,
    "yearBuilt": 1937,
    "lastRenovation": 2013,
    "fieldType": "Natural Grass",
    "surfaceQuality": 92,
    "fanExperience": 66,
    "homeFieldAdvantage": 84,
    "noiseRating": 88,
    "clubSeats": 3716,
    "suites": 1033
  },
  {
    "stadiumId": "stadium_stanford",
    "schoolId": "school_stanford",
    "stadiumName": "Stanford Stadium",
    "city": "Stanford",
    "state": "CA",
    "capacity": 71488,
    "currentCapacity": 71488,
    "targetCapacity": 71488,
    "yearBuilt": 1921,
    "lastRenovation": 2008,
    "fieldType": "Natural Grass",
    "surfaceQuality": 72,
    "fanExperience": 92,
    "homeFieldAdvantage": 69,
    "noiseRating": 77,
    "clubSeats": 3728,
    "suites": 1147
  },
  {
    "stadiumId": "stadium_syracuse",
    "schoolId": "school_syracuse",
    "stadiumName": "Syracuse Stadium",
    "city": "Syracuse",
    "state": "NY",
    "capacity": 84305,
    "currentCapacity": 84305,
    "targetCapacity": 84305,
    "yearBuilt": 1940,
    "lastRenovation": 2010,
    "fieldType": "Artificial Turf",
    "surfaceQuality": 87,
    "fanExperience": 74,
    "homeFieldAdvantage": 57,
    "noiseRating": 97,
    "clubSeats": 6587,
    "suites": 1878
  },
  {
    "stadiumId": "stadium_virginia",
    "schoolId": "school_virginia",
    "stadiumName": "Virginia Stadium",
    "city": "Charlottesville",
    "state": "VA",
    "capacity": 71157,
    "currentCapacity": 71157,
    "targetCapacity": 71157,
    "yearBuilt": 1928,
    "lastRenovation": 2013,
    "fieldType": "Artificial Turf",
    "surfaceQuality": 75,
    "fanExperience": 62,
    "homeFieldAdvantage": 61,
    "noiseRating": 86,
    "clubSeats": 6144,
    "suites": 519
  },
  {
    "stadiumId": "stadium_virginia_tech",
    "schoolId": "school_virginia_tech",
    "stadiumName": "Virginia Tech Stadium",
    "city": "Blacksburg",
    "state": "VA",
    "capacity": 86388,
    "currentCapacity": 86388,
    "targetCapacity": 86388,
    "yearBuilt": 1920,
    "lastRenovation": 2021,
    "fieldType": "Natural Grass",
    "surfaceQuality": 66,
    "fanExperience": 72,
    "homeFieldAdvantage": 63,
    "noiseRating": 59,
    "clubSeats": 4218,
    "suites": 1897
  },
  {
    "stadiumId": "stadium_wake_forest",
    "schoolId": "school_wake_forest",
    "stadiumName": "Wake Forest Stadium",
    "city": "Winston-Salem",
    "state": "NC",
    "capacity": 74106,
    "currentCapacity": 74106,
    "targetCapacity": 74106,
    "yearBuilt": 1994,
    "lastRenovation": 2024,
    "fieldType": "Artificial Turf",
    "surfaceQuality": 79,
    "fanExperience": 56,
    "homeFieldAdvantage": 72,
    "noiseRating": 72,
    "clubSeats": 6230,
    "suites": 1550
  },
  {
    "stadiumId": "stadium_illinois",
    "schoolId": "school_illinois",
    "stadiumName": "Illinois Stadium",
    "city": "Champaign",
    "state": "IL",
    "capacity": 69220,
    "currentCapacity": 69220,
    "targetCapacity": 69220,
    "yearBuilt": 1998,
    "lastRenovation": 2007,
    "fieldType": "Artificial Turf",
    "surfaceQuality": 55,
    "fanExperience": 76,
    "homeFieldAdvantage": 73,
    "noiseRating": 86,
    "clubSeats": 4129,
    "suites": 683
  },
  {
    "stadiumId": "stadium_indiana",
    "schoolId": "school_indiana",
    "stadiumName": "Indiana Stadium",
    "city": "Bloomington",
    "state": "IN",
    "capacity": 92573,
    "currentCapacity": 92573,
    "targetCapacity": 92573,
    "yearBuilt": 1976,
    "lastRenovation": 2024,
    "fieldType": "Artificial Turf",
    "surfaceQuality": 74,
    "fanExperience": 82,
    "homeFieldAdvantage": 62,
    "noiseRating": 92,
    "clubSeats": 5413,
    "suites": 942
  },
  {
    "stadiumId": "stadium_iowa",
    "schoolId": "school_iowa",
    "stadiumName": "Iowa Stadium",
    "city": "Iowa City",
    "state": "IA",
    "capacity": 92803,
    "currentCapacity": 92803,
    "targetCapacity": 92803,
    "yearBuilt": 2008,
    "lastRenovation": 2009,
    "fieldType": "Natural Grass",
    "surfaceQuality": 90,
    "fanExperience": 86,
    "homeFieldAdvantage": 69,
    "noiseRating": 77,
    "clubSeats": 3935,
    "suites": 1243
  },
  {
    "stadiumId": "stadium_maryland",
    "schoolId": "school_maryland",
    "stadiumName": "Maryland Stadium",
    "city": "College Park",
    "state": "MD",
    "capacity": 79890,
    "currentCapacity": 79890,
    "targetCapacity": 79890,
    "yearBuilt": 1963,
    "lastRenovation": 2026,
    "fieldType": "Artificial Turf",
    "surfaceQuality": 78,
    "fanExperience": 73,
    "homeFieldAdvantage": 54,
    "noiseRating": 99,
    "clubSeats": 4956,
    "suites": 1848
  },
  {
    "stadiumId": "stadium_michigan",
    "schoolId": "school_michigan",
    "stadiumName": "Michigan Stadium",
    "city": "Ann Arbor",
    "state": "MI",
    "capacity": 100174,
    "currentCapacity": 100174,
    "targetCapacity": 100174,
    "yearBuilt": 1930,
    "lastRenovation": 2020,
    "fieldType": "Natural Grass",
    "surfaceQuality": 97,
    "fanExperience": 93,
    "homeFieldAdvantage": 99,
    "noiseRating": 94,
    "clubSeats": 3417,
    "suites": 2418
  },
  {
    "stadiumId": "stadium_michigan_state",
    "schoolId": "school_michigan_state",
    "stadiumName": "Michigan State Stadium",
    "city": "East Lansing",
    "state": "MI",
    "capacity": 75097,
    "currentCapacity": 75097,
    "targetCapacity": 75097,
    "yearBuilt": 1959,
    "lastRenovation": 2023,
    "fieldType": "Artificial Turf",
    "surfaceQuality": 66,
    "fanExperience": 50,
    "homeFieldAdvantage": 76,
    "noiseRating": 83,
    "clubSeats": 5079,
    "suites": 528
  },
  {
    "stadiumId": "stadium_minnesota",
    "schoolId": "school_minnesota",
    "stadiumName": "Minnesota Stadium",
    "city": "Minneapolis",
    "state": "MN",
    "capacity": 87356,
    "currentCapacity": 87356,
    "targetCapacity": 87356,
    "yearBuilt": 2001,
    "lastRenovation": 2019,
    "fieldType": "Natural Grass",
    "surfaceQuality": 62,
    "fanExperience": 85,
    "homeFieldAdvantage": 86,
    "noiseRating": 75,
    "clubSeats": 6856,
    "suites": 1377
  },
  {
    "stadiumId": "stadium_nebraska",
    "schoolId": "school_nebraska",
    "stadiumName": "Nebraska Stadium",
    "city": "Lincoln",
    "state": "NE",
    "capacity": 90879,
    "currentCapacity": 90879,
    "targetCapacity": 90879,
    "yearBuilt": 1947,
    "lastRenovation": 2016,
    "fieldType": "Artificial Turf",
    "surfaceQuality": 80,
    "fanExperience": 72,
    "homeFieldAdvantage": 99,
    "noiseRating": 82,
    "clubSeats": 2781,
    "suites": 2177
  },
  {
    "stadiumId": "stadium_northwestern",
    "schoolId": "school_northwestern",
    "stadiumName": "Northwestern Stadium",
    "city": "Evanston",
    "state": "IL",
    "capacity": 74736,
    "currentCapacity": 74736,
    "targetCapacity": 74736,
    "yearBuilt": 1967,
    "lastRenovation": 2020,
    "fieldType": "Artificial Turf",
    "surfaceQuality": 51,
    "fanExperience": 75,
    "homeFieldAdvantage": 57,
    "noiseRating": 84,
    "clubSeats": 3456,
    "suites": 749
  },
  {
    "stadiumId": "stadium_ohio_state",
    "schoolId": "school_ohio_state",
    "stadiumName": "Ohio State Stadium",
    "city": "Columbus",
    "state": "OH",
    "capacity": 91098,
    "currentCapacity": 91098,
    "targetCapacity": 91098,
    "yearBuilt": 1921,
    "lastRenovation": 2022,
    "fieldType": "Natural Grass",
    "surfaceQuality": 95,
    "fanExperience": 84,
    "homeFieldAdvantage": 99,
    "noiseRating": 70,
    "clubSeats": 3423,
    "suites": 2037
  },
  {
    "stadiumId": "stadium_oregon",
    "schoolId": "school_oregon",
    "stadiumName": "Oregon Stadium",
    "city": "Eugene",
    "state": "OR",
    "capacity": 110000,
    "currentCapacity": 110000,
    "targetCapacity": 110000,
    "yearBuilt": 2000,
    "lastRenovation": 2026,
    "fieldType": "Natural Grass",
    "surfaceQuality": 99,
    "fanExperience": 99,
    "homeFieldAdvantage": 99,
    "noiseRating": 93,
    "clubSeats": 4938,
    "suites": 1777
  },
  {
    "stadiumId": "stadium_penn_state",
    "schoolId": "school_penn_state",
    "stadiumName": "Penn State Stadium",
    "city": "University Park",
    "state": "PA",
    "capacity": 90992,
    "currentCapacity": 90992,
    "targetCapacity": 90992,
    "yearBuilt": 1942,
    "lastRenovation": 2022,
    "fieldType": "Natural Grass",
    "surfaceQuality": 89,
    "fanExperience": 99,
    "homeFieldAdvantage": 99,
    "noiseRating": 89,
    "clubSeats": 2907,
    "suites": 979
  },
  {
    "stadiumId": "stadium_purdue",
    "schoolId": "school_purdue",
    "stadiumName": "Purdue Stadium",
    "city": "West Lafayette",
    "state": "IN",
    "capacity": 58515,
    "currentCapacity": 58515,
    "targetCapacity": 58515,
    "yearBuilt": 1938,
    "lastRenovation": 2007,
    "fieldType": "Natural Grass",
    "surfaceQuality": 73,
    "fanExperience": 78,
    "homeFieldAdvantage": 69,
    "noiseRating": 52,
    "clubSeats": 2768,
    "suites": 438
  },
  {
    "stadiumId": "stadium_rutgers",
    "schoolId": "school_rutgers",
    "stadiumName": "Rutgers Stadium",
    "city": "Piscataway",
    "state": "NJ",
    "capacity": 67645,
    "currentCapacity": 67645,
    "targetCapacity": 67645,
    "yearBuilt": 1942,
    "lastRenovation": 2020,
    "fieldType": "Artificial Turf",
    "surfaceQuality": 68,
    "fanExperience": 83,
    "homeFieldAdvantage": 72,
    "noiseRating": 60,
    "clubSeats": 4025,
    "suites": 461
  },
  {
    "stadiumId": "stadium_ucla",
    "schoolId": "school_ucla",
    "stadiumName": "UCLA Stadium",
    "city": "Los Angeles",
    "state": "CA",
    "capacity": 98067,
    "currentCapacity": 98067,
    "targetCapacity": 98067,
    "yearBuilt": 1961,
    "lastRenovation": 2008,
    "fieldType": "Artificial Turf",
    "surfaceQuality": 82,
    "fanExperience": 53,
    "homeFieldAdvantage": 94,
    "noiseRating": 70,
    "clubSeats": 5660,
    "suites": 596
  },
  {
    "stadiumId": "stadium_usc",
    "schoolId": "school_usc",
    "stadiumName": "USC Stadium",
    "city": "Los Angeles",
    "state": "CA",
    "capacity": 104381,
    "currentCapacity": 104381,
    "targetCapacity": 104381,
    "yearBuilt": 1948,
    "lastRenovation": 2008,
    "fieldType": "Artificial Turf",
    "surfaceQuality": 97,
    "fanExperience": 99,
    "homeFieldAdvantage": 90,
    "noiseRating": 99,
    "clubSeats": 4959,
    "suites": 1994
  },
  {
    "stadiumId": "stadium_washington",
    "schoolId": "school_washington",
    "stadiumName": "Washington Stadium",
    "city": "Seattle",
    "state": "WA",
    "capacity": 81925,
    "currentCapacity": 81925,
    "targetCapacity": 81925,
    "yearBuilt": 1956,
    "lastRenovation": 2014,
    "fieldType": "Artificial Turf",
    "surfaceQuality": 91,
    "fanExperience": 74,
    "homeFieldAdvantage": 73,
    "noiseRating": 85,
    "clubSeats": 6207,
    "suites": 1027
  },
  {
    "stadiumId": "stadium_wisconsin",
    "schoolId": "school_wisconsin",
    "stadiumName": "Wisconsin Stadium",
    "city": "Madison",
    "state": "WI",
    "capacity": 93993,
    "currentCapacity": 93993,
    "targetCapacity": 93993,
    "yearBuilt": 1932,
    "lastRenovation": 2019,
    "fieldType": "Natural Grass",
    "surfaceQuality": 81,
    "fanExperience": 70,
    "homeFieldAdvantage": 81,
    "noiseRating": 81,
    "clubSeats": 6512,
    "suites": 760
  },
  {
    "stadiumId": "stadium_arizona",
    "schoolId": "school_arizona",
    "stadiumName": "Arizona Stadium",
    "city": "Tucson",
    "state": "AZ",
    "capacity": 83776,
    "currentCapacity": 83776,
    "targetCapacity": 83776,
    "yearBuilt": 1949,
    "lastRenovation": 2007,
    "fieldType": "Artificial Turf",
    "surfaceQuality": 89,
    "fanExperience": 69,
    "homeFieldAdvantage": 70,
    "noiseRating": 66,
    "clubSeats": 3349,
    "suites": 920
  },
  {
    "stadiumId": "stadium_arizona_state",
    "schoolId": "school_arizona_state",
    "stadiumName": "Arizona State Stadium",
    "city": "Tempe",
    "state": "AZ",
    "capacity": 86870,
    "currentCapacity": 86870,
    "targetCapacity": 86870,
    "yearBuilt": 1979,
    "lastRenovation": 2025,
    "fieldType": "Artificial Turf",
    "surfaceQuality": 75,
    "fanExperience": 61,
    "homeFieldAdvantage": 82,
    "noiseRating": 90,
    "clubSeats": 4105,
    "suites": 1384
  },
  {
    "stadiumId": "stadium_baylor",
    "schoolId": "school_baylor",
    "stadiumName": "Baylor Stadium",
    "city": "Waco",
    "state": "TX",
    "capacity": 82622,
    "currentCapacity": 82622,
    "targetCapacity": 82622,
    "yearBuilt": 1957,
    "lastRenovation": 2014,
    "fieldType": "Natural Grass",
    "surfaceQuality": 81,
    "fanExperience": 64,
    "homeFieldAdvantage": 64,
    "noiseRating": 83,
    "clubSeats": 5878,
    "suites": 1643
  },
  {
    "stadiumId": "stadium_byu",
    "schoolId": "school_byu",
    "stadiumName": "BYU Stadium",
    "city": "Provo",
    "state": "UT",
    "capacity": 69775,
    "currentCapacity": 69775,
    "targetCapacity": 69775,
    "yearBuilt": 1931,
    "lastRenovation": 2014,
    "fieldType": "Artificial Turf",
    "surfaceQuality": 70,
    "fanExperience": 78,
    "homeFieldAdvantage": 71,
    "noiseRating": 89,
    "clubSeats": 6160,
    "suites": 1089
  },
  {
    "stadiumId": "stadium_cincinnati",
    "schoolId": "school_cincinnati",
    "stadiumName": "Cincinnati Stadium",
    "city": "Cincinnati",
    "state": "OH",
    "capacity": 77003,
    "currentCapacity": 77003,
    "targetCapacity": 77003,
    "yearBuilt": 1921,
    "lastRenovation": 2013,
    "fieldType": "Natural Grass",
    "surfaceQuality": 55,
    "fanExperience": 74,
    "homeFieldAdvantage": 62,
    "noiseRating": 54,
    "clubSeats": 6109,
    "suites": 1833
  },
  {
    "stadiumId": "stadium_colorado",
    "schoolId": "school_colorado",
    "stadiumName": "Colorado Stadium",
    "city": "Boulder",
    "state": "CO",
    "capacity": 90534,
    "currentCapacity": 90534,
    "targetCapacity": 90534,
    "yearBuilt": 1983,
    "lastRenovation": 2008,
    "fieldType": "Natural Grass",
    "surfaceQuality": 76,
    "fanExperience": 80,
    "homeFieldAdvantage": 94,
    "noiseRating": 69,
    "clubSeats": 7873,
    "suites": 1713
  },
  {
    "stadiumId": "stadium_houston",
    "schoolId": "school_houston",
    "stadiumName": "Houston Stadium",
    "city": "Houston",
    "state": "TX",
    "capacity": 86285,
    "currentCapacity": 86285,
    "targetCapacity": 86285,
    "yearBuilt": 1966,
    "lastRenovation": 2008,
    "fieldType": "Artificial Turf",
    "surfaceQuality": 39,
    "fanExperience": 57,
    "homeFieldAdvantage": 58,
    "noiseRating": 76,
    "clubSeats": 3571,
    "suites": 642
  },
  {
    "stadiumId": "stadium_iowa_state",
    "schoolId": "school_iowa_state",
    "stadiumName": "Iowa State Stadium",
    "city": "Ames",
    "state": "IA",
    "capacity": 80190,
    "currentCapacity": 80190,
    "targetCapacity": 80190,
    "yearBuilt": 1996,
    "lastRenovation": 2005,
    "fieldType": "Artificial Turf",
    "surfaceQuality": 83,
    "fanExperience": 82,
    "homeFieldAdvantage": 73,
    "noiseRating": 85,
    "clubSeats": 3245,
    "suites": 1461
  },
  {
    "stadiumId": "stadium_kansas",
    "schoolId": "school_kansas",
    "stadiumName": "Kansas Stadium",
    "city": "Lawrence",
    "state": "KS",
    "capacity": 57616,
    "currentCapacity": 57616,
    "targetCapacity": 57616,
    "yearBuilt": 1984,
    "lastRenovation": 2012,
    "fieldType": "Natural Grass",
    "surfaceQuality": 55,
    "fanExperience": 32,
    "homeFieldAdvantage": 52,
    "noiseRating": 49,
    "clubSeats": 3952,
    "suites": 323
  },
  {
    "stadiumId": "stadium_kansas_state",
    "schoolId": "school_kansas_state",
    "stadiumName": "Kansas State Stadium",
    "city": "Manhattan",
    "state": "KS",
    "capacity": 77784,
    "currentCapacity": 77784,
    "targetCapacity": 77784,
    "yearBuilt": 1997,
    "lastRenovation": 2018,
    "fieldType": "Natural Grass",
    "surfaceQuality": 83,
    "fanExperience": 87,
    "homeFieldAdvantage": 79,
    "noiseRating": 70,
    "clubSeats": 4906,
    "suites": 1735
  },
  {
    "stadiumId": "stadium_oklahoma_state",
    "schoolId": "school_oklahoma_state",
    "stadiumName": "Oklahoma State Stadium",
    "city": "Stillwater",
    "state": "OK",
    "capacity": 92711,
    "currentCapacity": 92711,
    "targetCapacity": 92711,
    "yearBuilt": 1931,
    "lastRenovation": 2018,
    "fieldType": "Natural Grass",
    "surfaceQuality": 84,
    "fanExperience": 72,
    "homeFieldAdvantage": 87,
    "noiseRating": 87,
    "clubSeats": 8102,
    "suites": 1505
  },
  {
    "stadiumId": "stadium_tcu",
    "schoolId": "school_tcu",
    "stadiumName": "TCU Stadium",
    "city": "Fort Worth",
    "state": "TX",
    "capacity": 81194,
    "currentCapacity": 81194,
    "targetCapacity": 81194,
    "yearBuilt": 1991,
    "lastRenovation": 2016,
    "fieldType": "Natural Grass",
    "surfaceQuality": 80,
    "fanExperience": 76,
    "homeFieldAdvantage": 59,
    "noiseRating": 84,
    "clubSeats": 7183,
    "suites": 1734
  },
  {
    "stadiumId": "stadium_texas_tech",
    "schoolId": "school_texas_tech",
    "stadiumName": "Texas Tech Stadium",
    "city": "Lubbock",
    "state": "TX",
    "capacity": 94895,
    "currentCapacity": 94895,
    "targetCapacity": 94895,
    "yearBuilt": 2004,
    "lastRenovation": 2017,
    "fieldType": "Natural Grass",
    "surfaceQuality": 83,
    "fanExperience": 87,
    "homeFieldAdvantage": 94,
    "noiseRating": 78,
    "clubSeats": 4071,
    "suites": 1271
  },
  {
    "stadiumId": "stadium_ucf",
    "schoolId": "school_ucf",
    "stadiumName": "UCF Stadium",
    "city": "Orlando",
    "state": "FL",
    "capacity": 69720,
    "currentCapacity": 69720,
    "targetCapacity": 69720,
    "yearBuilt": 1947,
    "lastRenovation": 2021,
    "fieldType": "Natural Grass",
    "surfaceQuality": 64,
    "fanExperience": 67,
    "homeFieldAdvantage": 75,
    "noiseRating": 62,
    "clubSeats": 4295,
    "suites": 778
  },
  {
    "stadiumId": "stadium_utah",
    "schoolId": "school_utah",
    "stadiumName": "Utah Stadium",
    "city": "Salt Lake City",
    "state": "UT",
    "capacity": 89111,
    "currentCapacity": 89111,
    "targetCapacity": 89111,
    "yearBuilt": 2010,
    "lastRenovation": 2012,
    "fieldType": "Artificial Turf",
    "surfaceQuality": 99,
    "fanExperience": 91,
    "homeFieldAdvantage": 83,
    "noiseRating": 82,
    "clubSeats": 7598,
    "suites": 1982
  },
  {
    "stadiumId": "stadium_west_virginia",
    "schoolId": "school_west_virginia",
    "stadiumName": "West Virginia Stadium",
    "city": "Morgantown",
    "state": "WV",
    "capacity": 71429,
    "currentCapacity": 71429,
    "targetCapacity": 71429,
    "yearBuilt": 1930,
    "lastRenovation": 2017,
    "fieldType": "Artificial Turf",
    "surfaceQuality": 78,
    "fanExperience": 74,
    "homeFieldAdvantage": 66,
    "noiseRating": 75,
    "clubSeats": 4856,
    "suites": 1115
  },
  {
    "stadiumId": "stadium_alabama",
    "schoolId": "school_alabama",
    "stadiumName": "Alabama Stadium",
    "city": "Tuscaloosa",
    "state": "AL",
    "capacity": 96296,
    "currentCapacity": 96296,
    "targetCapacity": 96296,
    "yearBuilt": 2002,
    "lastRenovation": 2025,
    "fieldType": "Artificial Turf",
    "surfaceQuality": 99,
    "fanExperience": 78,
    "homeFieldAdvantage": 94,
    "noiseRating": 95,
    "clubSeats": 5443,
    "suites": 1064
  },
  {
    "stadiumId": "stadium_arkansas",
    "schoolId": "school_arkansas",
    "stadiumName": "Arkansas Stadium",
    "city": "Fayetteville",
    "state": "AR",
    "capacity": 61274,
    "currentCapacity": 61274,
    "targetCapacity": 61274,
    "yearBuilt": 1925,
    "lastRenovation": 2019,
    "fieldType": "Natural Grass",
    "surfaceQuality": 63,
    "fanExperience": 63,
    "homeFieldAdvantage": 81,
    "noiseRating": 72,
    "clubSeats": 2218,
    "suites": 1408
  },
  {
    "stadiumId": "stadium_auburn",
    "schoolId": "school_auburn",
    "stadiumName": "Auburn Stadium",
    "city": "Auburn",
    "state": "AL",
    "capacity": 84239,
    "currentCapacity": 84239,
    "targetCapacity": 84239,
    "yearBuilt": 2006,
    "lastRenovation": 2024,
    "fieldType": "Natural Grass",
    "surfaceQuality": 87,
    "fanExperience": 66,
    "homeFieldAdvantage": 88,
    "noiseRating": 85,
    "clubSeats": 5955,
    "suites": 899
  },
  {
    "stadiumId": "stadium_florida",
    "schoolId": "school_florida",
    "stadiumName": "Florida Stadium",
    "city": "Gainesville",
    "state": "FL",
    "capacity": 94782,
    "currentCapacity": 94782,
    "targetCapacity": 94782,
    "yearBuilt": 2014,
    "lastRenovation": 2026,
    "fieldType": "Natural Grass",
    "surfaceQuality": 74,
    "fanExperience": 80,
    "homeFieldAdvantage": 78,
    "noiseRating": 80,
    "clubSeats": 3868,
    "suites": 879
  },
  {
    "stadiumId": "stadium_georgia",
    "schoolId": "school_georgia",
    "stadiumName": "Georgia Stadium",
    "city": "Athens",
    "state": "GA",
    "capacity": 78437,
    "currentCapacity": 78437,
    "targetCapacity": 78437,
    "yearBuilt": 1943,
    "lastRenovation": 2024,
    "fieldType": "Natural Grass",
    "surfaceQuality": 94,
    "fanExperience": 91,
    "homeFieldAdvantage": 82,
    "noiseRating": 99,
    "clubSeats": 6916,
    "suites": 1350
  },
  {
    "stadiumId": "stadium_kentucky",
    "schoolId": "school_kentucky",
    "stadiumName": "Kentucky Stadium",
    "city": "Lexington",
    "state": "KY",
    "capacity": 88501,
    "currentCapacity": 88501,
    "targetCapacity": 88501,
    "yearBuilt": 1937,
    "lastRenovation": 2013,
    "fieldType": "Natural Grass",
    "surfaceQuality": 61,
    "fanExperience": 62,
    "homeFieldAdvantage": 58,
    "noiseRating": 71,
    "clubSeats": 7146,
    "suites": 1949
  },
  {
    "stadiumId": "stadium_lsu",
    "schoolId": "school_lsu",
    "stadiumName": "LSU Stadium",
    "city": "Baton Rouge",
    "state": "LA",
    "capacity": 75314,
    "currentCapacity": 75314,
    "targetCapacity": 75314,
    "yearBuilt": 1969,
    "lastRenovation": 2007,
    "fieldType": "Artificial Turf",
    "surfaceQuality": 93,
    "fanExperience": 99,
    "homeFieldAdvantage": 99,
    "noiseRating": 99,
    "clubSeats": 3774,
    "suites": 596
  },
  {
    "stadiumId": "stadium_mississippi_state",
    "schoolId": "school_mississippi_state",
    "stadiumName": "Mississippi State Stadium",
    "city": "Starkville",
    "state": "MS",
    "capacity": 73855,
    "currentCapacity": 73855,
    "targetCapacity": 73855,
    "yearBuilt": 1950,
    "lastRenovation": 2018,
    "fieldType": "Artificial Turf",
    "surfaceQuality": 70,
    "fanExperience": 86,
    "homeFieldAdvantage": 74,
    "noiseRating": 49,
    "clubSeats": 5016,
    "suites": 1218
  },
  {
    "stadiumId": "stadium_missouri",
    "schoolId": "school_missouri",
    "stadiumName": "Missouri Stadium",
    "city": "Columbia",
    "state": "MO",
    "capacity": 79948,
    "currentCapacity": 79948,
    "targetCapacity": 79948,
    "yearBuilt": 1980,
    "lastRenovation": 2006,
    "fieldType": "Artificial Turf",
    "surfaceQuality": 84,
    "fanExperience": 75,
    "homeFieldAdvantage": 97,
    "noiseRating": 78,
    "clubSeats": 4052,
    "suites": 1571
  },
  {
    "stadiumId": "stadium_oklahoma",
    "schoolId": "school_oklahoma",
    "stadiumName": "Oklahoma Stadium",
    "city": "Norman",
    "state": "OK",
    "capacity": 95873,
    "currentCapacity": 95873,
    "targetCapacity": 95873,
    "yearBuilt": 1945,
    "lastRenovation": 2006,
    "fieldType": "Artificial Turf",
    "surfaceQuality": 99,
    "fanExperience": 99,
    "homeFieldAdvantage": 92,
    "noiseRating": 99,
    "clubSeats": 4333,
    "suites": 1923
  },
  {
    "stadiumId": "stadium_ole_miss",
    "schoolId": "school_ole_miss",
    "stadiumName": "Ole Miss Stadium",
    "city": "Oxford",
    "state": "MS",
    "capacity": 88210,
    "currentCapacity": 88210,
    "targetCapacity": 88210,
    "yearBuilt": 1967,
    "lastRenovation": 2021,
    "fieldType": "Artificial Turf",
    "surfaceQuality": 86,
    "fanExperience": 63,
    "homeFieldAdvantage": 95,
    "noiseRating": 89,
    "clubSeats": 6998,
    "suites": 1403
  },
  {
    "stadiumId": "stadium_south_carolina",
    "schoolId": "school_south_carolina",
    "stadiumName": "South Carolina Stadium",
    "city": "Columbia",
    "state": "SC",
    "capacity": 72633,
    "currentCapacity": 72633,
    "targetCapacity": 72633,
    "yearBuilt": 1985,
    "lastRenovation": 2026,
    "fieldType": "Natural Grass",
    "surfaceQuality": 61,
    "fanExperience": 76,
    "homeFieldAdvantage": 68,
    "noiseRating": 52,
    "clubSeats": 2330,
    "suites": 460
  },
  {
    "stadiumId": "stadium_tennessee",
    "schoolId": "school_tennessee",
    "stadiumName": "Tennessee Stadium",
    "city": "Knoxville",
    "state": "TN",
    "capacity": 100600,
    "currentCapacity": 100600,
    "targetCapacity": 100600,
    "yearBuilt": 2003,
    "lastRenovation": 2013,
    "fieldType": "Natural Grass",
    "surfaceQuality": 90,
    "fanExperience": 87,
    "homeFieldAdvantage": 94,
    "noiseRating": 99,
    "clubSeats": 8532,
    "suites": 739
  },
  {
    "stadiumId": "stadium_texas",
    "schoolId": "school_texas",
    "stadiumName": "Texas Stadium",
    "city": "Austin",
    "state": "TX",
    "capacity": 85310,
    "currentCapacity": 85310,
    "targetCapacity": 85310,
    "yearBuilt": 1958,
    "lastRenovation": 2010,
    "fieldType": "Natural Grass",
    "surfaceQuality": 89,
    "fanExperience": 96,
    "homeFieldAdvantage": 78,
    "noiseRating": 98,
    "clubSeats": 3270,
    "suites": 1775
  },
  {
    "stadiumId": "stadium_texas_a_m",
    "schoolId": "school_texas_a_m",
    "stadiumName": "Texas A&M Stadium",
    "city": "College Station",
    "state": "TX",
    "capacity": 86241,
    "currentCapacity": 86241,
    "targetCapacity": 86241,
    "yearBuilt": 1960,
    "lastRenovation": 2025,
    "fieldType": "Natural Grass",
    "surfaceQuality": 64,
    "fanExperience": 84,
    "homeFieldAdvantage": 64,
    "noiseRating": 99,
    "clubSeats": 6624,
    "suites": 1534
  },
  {
    "stadiumId": "stadium_vanderbilt",
    "schoolId": "school_vanderbilt",
    "stadiumName": "Vanderbilt Stadium",
    "city": "Nashville",
    "state": "TN",
    "capacity": 67372,
    "currentCapacity": 67372,
    "targetCapacity": 67372,
    "yearBuilt": 1936,
    "lastRenovation": 2025,
    "fieldType": "Artificial Turf",
    "surfaceQuality": 58,
    "fanExperience": 63,
    "homeFieldAdvantage": 63,
    "noiseRating": 56,
    "clubSeats": 4368,
    "suites": 567
  },
  {
    "stadiumId": "stadium_army",
    "schoolId": "school_army",
    "stadiumName": "Army Stadium",
    "city": "West Point",
    "state": "NY",
    "capacity": 74066,
    "currentCapacity": 74066,
    "targetCapacity": 74066,
    "yearBuilt": 1981,
    "lastRenovation": 2012,
    "fieldType": "Artificial Turf",
    "surfaceQuality": 56,
    "fanExperience": 61,
    "homeFieldAdvantage": 69,
    "noiseRating": 62,
    "clubSeats": 4373,
    "suites": 672
  },
  {
    "stadiumId": "stadium_charlotte",
    "schoolId": "school_charlotte",
    "stadiumName": "Charlotte Stadium",
    "city": "Charlotte",
    "state": "NC",
    "capacity": 67155,
    "currentCapacity": 67155,
    "targetCapacity": 67155,
    "yearBuilt": 1932,
    "lastRenovation": 2006,
    "fieldType": "Artificial Turf",
    "surfaceQuality": 65,
    "fanExperience": 80,
    "homeFieldAdvantage": 49,
    "noiseRating": 28,
    "clubSeats": 5650,
    "suites": 1428
  },
  {
    "stadiumId": "stadium_east_carolina",
    "schoolId": "school_east_carolina",
    "stadiumName": "East Carolina Stadium",
    "city": "Greenville",
    "state": "NC",
    "capacity": 67264,
    "currentCapacity": 67264,
    "targetCapacity": 67264,
    "yearBuilt": 1965,
    "lastRenovation": 2006,
    "fieldType": "Natural Grass",
    "surfaceQuality": 53,
    "fanExperience": 72,
    "homeFieldAdvantage": 66,
    "noiseRating": 40,
    "clubSeats": 3171,
    "suites": 347
  },
  {
    "stadiumId": "stadium_florida_atlantic",
    "schoolId": "school_florida_atlantic",
    "stadiumName": "Florida Atlantic Stadium",
    "city": "Boca Raton",
    "state": "FL",
    "capacity": 45877,
    "currentCapacity": 45877,
    "targetCapacity": 45877,
    "yearBuilt": 1999,
    "lastRenovation": 2026,
    "fieldType": "Natural Grass",
    "surfaceQuality": 45,
    "fanExperience": 45,
    "homeFieldAdvantage": 45,
    "noiseRating": 14,
    "clubSeats": 2911,
    "suites": 564
  },
  {
    "stadiumId": "stadium_memphis",
    "schoolId": "school_memphis",
    "stadiumName": "Memphis Stadium",
    "city": "Memphis",
    "state": "TN",
    "capacity": 72180,
    "currentCapacity": 72180,
    "targetCapacity": 72180,
    "yearBuilt": 1998,
    "lastRenovation": 2014,
    "fieldType": "Artificial Turf",
    "surfaceQuality": 52,
    "fanExperience": 63,
    "homeFieldAdvantage": 49,
    "noiseRating": 65,
    "clubSeats": 4222,
    "suites": 384
  },
  {
    "stadiumId": "stadium_navy",
    "schoolId": "school_navy",
    "stadiumName": "Navy Stadium",
    "city": "Annapolis",
    "state": "MD",
    "capacity": 47382,
    "currentCapacity": 47382,
    "targetCapacity": 47382,
    "yearBuilt": 1968,
    "lastRenovation": 2009,
    "fieldType": "Natural Grass",
    "surfaceQuality": 46,
    "fanExperience": 77,
    "homeFieldAdvantage": 54,
    "noiseRating": 50,
    "clubSeats": 2313,
    "suites": 380
  },
  {
    "stadiumId": "stadium_north_texas",
    "schoolId": "school_north_texas",
    "stadiumName": "North Texas Stadium",
    "city": "Denton",
    "state": "TX",
    "capacity": 59533,
    "currentCapacity": 59533,
    "targetCapacity": 59533,
    "yearBuilt": 1942,
    "lastRenovation": 2019,
    "fieldType": "Artificial Turf",
    "surfaceQuality": 46,
    "fanExperience": 55,
    "homeFieldAdvantage": 72,
    "noiseRating": 45,
    "clubSeats": 4656,
    "suites": 612
  },
  {
    "stadiumId": "stadium_rice",
    "schoolId": "school_rice",
    "stadiumName": "Rice Stadium",
    "city": "Houston",
    "state": "TX",
    "capacity": 55013,
    "currentCapacity": 55013,
    "targetCapacity": 55013,
    "yearBuilt": 1970,
    "lastRenovation": 2016,
    "fieldType": "Natural Grass",
    "surfaceQuality": 47,
    "fanExperience": 51,
    "homeFieldAdvantage": 63,
    "noiseRating": 50,
    "clubSeats": 3110,
    "suites": 557
  },
  {
    "stadiumId": "stadium_temple",
    "schoolId": "school_temple",
    "stadiumName": "Temple Stadium",
    "city": "Philadelphia",
    "state": "PA",
    "capacity": 57148,
    "currentCapacity": 57148,
    "targetCapacity": 57148,
    "yearBuilt": 1932,
    "lastRenovation": 2018,
    "fieldType": "Artificial Turf",
    "surfaceQuality": 52,
    "fanExperience": 48,
    "homeFieldAdvantage": 53,
    "noiseRating": 52,
    "clubSeats": 3601,
    "suites": 1347
  },
  {
    "stadiumId": "stadium_tulane",
    "schoolId": "school_tulane",
    "stadiumName": "Tulane Stadium",
    "city": "New Orleans",
    "state": "LA",
    "capacity": 79733,
    "currentCapacity": 79733,
    "targetCapacity": 79733,
    "yearBuilt": 1924,
    "lastRenovation": 2017,
    "fieldType": "Artificial Turf",
    "surfaceQuality": 64,
    "fanExperience": 76,
    "homeFieldAdvantage": 86,
    "noiseRating": 75,
    "clubSeats": 2571,
    "suites": 874
  },
  {
    "stadiumId": "stadium_tulsa",
    "schoolId": "school_tulsa",
    "stadiumName": "Tulsa Stadium",
    "city": "Tulsa",
    "state": "OK",
    "capacity": 59759,
    "currentCapacity": 59759,
    "targetCapacity": 59759,
    "yearBuilt": 2011,
    "lastRenovation": 2010,
    "fieldType": "Natural Grass",
    "surfaceQuality": 56,
    "fanExperience": 36,
    "homeFieldAdvantage": 39,
    "noiseRating": 48,
    "clubSeats": 2422,
    "suites": 1322
  },
  {
    "stadiumId": "stadium_uab",
    "schoolId": "school_uab",
    "stadiumName": "UAB Stadium",
    "city": "Birmingham",
    "state": "AL",
    "capacity": 81514,
    "currentCapacity": 81514,
    "targetCapacity": 81514,
    "yearBuilt": 2012,
    "lastRenovation": 2023,
    "fieldType": "Natural Grass",
    "surfaceQuality": 64,
    "fanExperience": 65,
    "homeFieldAdvantage": 77,
    "noiseRating": 68,
    "clubSeats": 4721,
    "suites": 667
  },
  {
    "stadiumId": "stadium_usf",
    "schoolId": "school_usf",
    "stadiumName": "USF Stadium",
    "city": "Tampa",
    "state": "FL",
    "capacity": 74028,
    "currentCapacity": 74028,
    "targetCapacity": 74028,
    "yearBuilt": 2005,
    "lastRenovation": 2011,
    "fieldType": "Natural Grass",
    "surfaceQuality": 53,
    "fanExperience": 44,
    "homeFieldAdvantage": 62,
    "noiseRating": 44,
    "clubSeats": 4566,
    "suites": 905
  },
  {
    "stadiumId": "stadium_utsa",
    "schoolId": "school_utsa",
    "stadiumName": "UTSA Stadium",
    "city": "San Antonio",
    "state": "TX",
    "capacity": 56859,
    "currentCapacity": 56859,
    "targetCapacity": 56859,
    "yearBuilt": 1978,
    "lastRenovation": 2023,
    "fieldType": "Natural Grass",
    "surfaceQuality": 59,
    "fanExperience": 39,
    "homeFieldAdvantage": 50,
    "noiseRating": 55,
    "clubSeats": 2573,
    "suites": 287
  },
  {
    "stadiumId": "stadium_delaware",
    "schoolId": "school_delaware",
    "stadiumName": "Delaware Stadium",
    "city": "Newark",
    "state": "DE",
    "capacity": 57915,
    "currentCapacity": 57915,
    "targetCapacity": 57915,
    "yearBuilt": 1968,
    "lastRenovation": 2019,
    "fieldType": "Artificial Turf",
    "surfaceQuality": 33,
    "fanExperience": 57,
    "homeFieldAdvantage": 36,
    "noiseRating": 30,
    "clubSeats": 4008,
    "suites": 692
  },
  {
    "stadiumId": "stadium_fiu",
    "schoolId": "school_fiu",
    "stadiumName": "FIU Stadium",
    "city": "Miami",
    "state": "FL",
    "capacity": 53993,
    "currentCapacity": 53993,
    "targetCapacity": 53993,
    "yearBuilt": 2012,
    "lastRenovation": 2008,
    "fieldType": "Natural Grass",
    "surfaceQuality": 50,
    "fanExperience": 48,
    "homeFieldAdvantage": 31,
    "noiseRating": 46,
    "clubSeats": 1670,
    "suites": 492
  },
  {
    "stadiumId": "stadium_jacksonville_state",
    "schoolId": "school_jacksonville_state",
    "stadiumName": "Jacksonville State Stadium",
    "city": "Jacksonville",
    "state": "AL",
    "capacity": 60489,
    "currentCapacity": 60489,
    "targetCapacity": 60489,
    "yearBuilt": 2013,
    "lastRenovation": 2023,
    "fieldType": "Artificial Turf",
    "surfaceQuality": 26,
    "fanExperience": 31,
    "homeFieldAdvantage": 45,
    "noiseRating": 32,
    "clubSeats": 4994,
    "suites": 1494
  },
  {
    "stadiumId": "stadium_kennesaw_state",
    "schoolId": "school_kennesaw_state",
    "stadiumName": "Kennesaw State Stadium",
    "city": "Kennesaw",
    "state": "GA",
    "capacity": 61890,
    "currentCapacity": 61890,
    "targetCapacity": 61890,
    "yearBuilt": 1939,
    "lastRenovation": 2014,
    "fieldType": "Artificial Turf",
    "surfaceQuality": 63,
    "fanExperience": 60,
    "homeFieldAdvantage": 68,
    "noiseRating": 55,
    "clubSeats": 5041,
    "suites": 488
  },
  {
    "stadiumId": "stadium_liberty",
    "schoolId": "school_liberty",
    "stadiumName": "Liberty Stadium",
    "city": "Lynchburg",
    "state": "VA",
    "capacity": 79498,
    "currentCapacity": 79498,
    "targetCapacity": 79498,
    "yearBuilt": 1968,
    "lastRenovation": 2026,
    "fieldType": "Natural Grass",
    "surfaceQuality": 74,
    "fanExperience": 63,
    "homeFieldAdvantage": 70,
    "noiseRating": 48,
    "clubSeats": 5050,
    "suites": 1159
  },
  {
    "stadiumId": "stadium_middle_tennessee",
    "schoolId": "school_middle_tennessee",
    "stadiumName": "Middle Tennessee Stadium",
    "city": "Murfreesboro",
    "state": "TN",
    "capacity": 65364,
    "currentCapacity": 65364,
    "targetCapacity": 65364,
    "yearBuilt": 1965,
    "lastRenovation": 2014,
    "fieldType": "Artificial Turf",
    "surfaceQuality": 73,
    "fanExperience": 49,
    "homeFieldAdvantage": 84,
    "noiseRating": 42,
    "clubSeats": 4794,
    "suites": 1322
  },
  {
    "stadiumId": "stadium_missouri_state",
    "schoolId": "school_missouri_state",
    "stadiumName": "Missouri State Stadium",
    "city": "Springfield",
    "state": "MO",
    "capacity": 82580,
    "currentCapacity": 82580,
    "targetCapacity": 82580,
    "yearBuilt": 1949,
    "lastRenovation": 2017,
    "fieldType": "Natural Grass",
    "surfaceQuality": 33,
    "fanExperience": 48,
    "homeFieldAdvantage": 44,
    "noiseRating": 39,
    "clubSeats": 6548,
    "suites": 2009
  },
  {
    "stadiumId": "stadium_new_mexico_state",
    "schoolId": "school_new_mexico_state",
    "stadiumName": "New Mexico State Stadium",
    "city": "Las Cruces",
    "state": "NM",
    "capacity": 53850,
    "currentCapacity": 53850,
    "targetCapacity": 53850,
    "yearBuilt": 1949,
    "lastRenovation": 2007,
    "fieldType": "Natural Grass",
    "surfaceQuality": 68,
    "fanExperience": 72,
    "homeFieldAdvantage": 59,
    "noiseRating": 45,
    "clubSeats": 3769,
    "suites": 933
  },
  {
    "stadiumId": "stadium_sam_houston",
    "schoolId": "school_sam_houston",
    "stadiumName": "Sam Houston Stadium",
    "city": "Huntsville",
    "state": "TX",
    "capacity": 63452,
    "currentCapacity": 63452,
    "targetCapacity": 63452,
    "yearBuilt": 1939,
    "lastRenovation": 2012,
    "fieldType": "Natural Grass",
    "surfaceQuality": 47,
    "fanExperience": 47,
    "homeFieldAdvantage": 40,
    "noiseRating": 71,
    "clubSeats": 2204,
    "suites": 1534
  },
  {
    "stadiumId": "stadium_western_kentucky",
    "schoolId": "school_western_kentucky",
    "stadiumName": "Western Kentucky Stadium",
    "city": "Bowling Green",
    "state": "KY",
    "capacity": 55243,
    "currentCapacity": 55243,
    "targetCapacity": 55243,
    "yearBuilt": 1930,
    "lastRenovation": 2020,
    "fieldType": "Artificial Turf",
    "surfaceQuality": 40,
    "fanExperience": 45,
    "homeFieldAdvantage": 43,
    "noiseRating": 87,
    "clubSeats": 4623,
    "suites": 1291
  },
  {
    "stadiumId": "stadium_akron",
    "schoolId": "school_akron",
    "stadiumName": "Akron Stadium",
    "city": "Akron",
    "state": "OH",
    "capacity": 58595,
    "currentCapacity": 58595,
    "targetCapacity": 58595,
    "yearBuilt": 1958,
    "lastRenovation": 2010,
    "fieldType": "Natural Grass",
    "surfaceQuality": 27,
    "fanExperience": 35,
    "homeFieldAdvantage": 38,
    "noiseRating": 30,
    "clubSeats": 3107,
    "suites": 1159
  },
  {
    "stadiumId": "stadium_ball_state",
    "schoolId": "school_ball_state",
    "stadiumName": "Ball State Stadium",
    "city": "Muncie",
    "state": "IN",
    "capacity": 73663,
    "currentCapacity": 73663,
    "targetCapacity": 73663,
    "yearBuilt": 1968,
    "lastRenovation": 2018,
    "fieldType": "Natural Grass",
    "surfaceQuality": 76,
    "fanExperience": 55,
    "homeFieldAdvantage": 47,
    "noiseRating": 78,
    "clubSeats": 5737,
    "suites": 1418
  },
  {
    "stadiumId": "stadium_bowling_green",
    "schoolId": "school_bowling_green",
    "stadiumName": "Bowling Green Stadium",
    "city": "Bowling Green",
    "state": "OH",
    "capacity": 56570,
    "currentCapacity": 56570,
    "targetCapacity": 56570,
    "yearBuilt": 1931,
    "lastRenovation": 2010,
    "fieldType": "Artificial Turf",
    "surfaceQuality": 28,
    "fanExperience": 45,
    "homeFieldAdvantage": 38,
    "noiseRating": 42,
    "clubSeats": 2898,
    "suites": 388
  },
  {
    "stadiumId": "stadium_buffalo",
    "schoolId": "school_buffalo",
    "stadiumName": "Buffalo Stadium",
    "city": "Buffalo",
    "state": "NY",
    "capacity": 67056,
    "currentCapacity": 67056,
    "targetCapacity": 67056,
    "yearBuilt": 1938,
    "lastRenovation": 2007,
    "fieldType": "Natural Grass",
    "surfaceQuality": 65,
    "fanExperience": 45,
    "homeFieldAdvantage": 62,
    "noiseRating": 52,
    "clubSeats": 3024,
    "suites": 665
  },
  {
    "stadiumId": "stadium_central_michigan",
    "schoolId": "school_central_michigan",
    "stadiumName": "Central Michigan Stadium",
    "city": "Mount Pleasant",
    "state": "MI",
    "capacity": 79489,
    "currentCapacity": 79489,
    "targetCapacity": 79489,
    "yearBuilt": 1961,
    "lastRenovation": 2024,
    "fieldType": "Natural Grass",
    "surfaceQuality": 52,
    "fanExperience": 59,
    "homeFieldAdvantage": 50,
    "noiseRating": 65,
    "clubSeats": 5889,
    "suites": 1403
  },
  {
    "stadiumId": "stadium_eastern_michigan",
    "schoolId": "school_eastern_michigan",
    "stadiumName": "Eastern Michigan Stadium",
    "city": "Ypsilanti",
    "state": "MI",
    "capacity": 72211,
    "currentCapacity": 72211,
    "targetCapacity": 72211,
    "yearBuilt": 1928,
    "lastRenovation": 2018,
    "fieldType": "Artificial Turf",
    "surfaceQuality": 38,
    "fanExperience": 63,
    "homeFieldAdvantage": 64,
    "noiseRating": 56,
    "clubSeats": 3999,
    "suites": 905
  },
  {
    "stadiumId": "stadium_kent_state",
    "schoolId": "school_kent_state",
    "stadiumName": "Kent State Stadium",
    "city": "Kent",
    "state": "OH",
    "capacity": 60089,
    "currentCapacity": 60089,
    "targetCapacity": 60089,
    "yearBuilt": 1941,
    "lastRenovation": 2025,
    "fieldType": "Natural Grass",
    "surfaceQuality": 39,
    "fanExperience": 45,
    "homeFieldAdvantage": 33,
    "noiseRating": 25,
    "clubSeats": 2998,
    "suites": 1257
  },
  {
    "stadiumId": "stadium_miami_oh",
    "schoolId": "school_miami_oh",
    "stadiumName": "Miami (OH) Stadium",
    "city": "Oxford",
    "state": "OH",
    "capacity": 49212,
    "currentCapacity": 49212,
    "targetCapacity": 49212,
    "yearBuilt": 1930,
    "lastRenovation": 2008,
    "fieldType": "Natural Grass",
    "surfaceQuality": 42,
    "fanExperience": 35,
    "homeFieldAdvantage": 50,
    "noiseRating": 44,
    "clubSeats": 2504,
    "suites": 342
  },
  {
    "stadiumId": "stadium_ohio",
    "schoolId": "school_ohio",
    "stadiumName": "Ohio Stadium",
    "city": "Athens",
    "state": "OH",
    "capacity": 59853,
    "currentCapacity": 59853,
    "targetCapacity": 59853,
    "yearBuilt": 1991,
    "lastRenovation": 2018,
    "fieldType": "Artificial Turf",
    "surfaceQuality": 62,
    "fanExperience": 73,
    "homeFieldAdvantage": 68,
    "noiseRating": 78,
    "clubSeats": 3347,
    "suites": 334
  },
  {
    "stadiumId": "stadium_toledo",
    "schoolId": "school_toledo",
    "stadiumName": "Toledo Stadium",
    "city": "Toledo",
    "state": "OH",
    "capacity": 69345,
    "currentCapacity": 69345,
    "targetCapacity": 69345,
    "yearBuilt": 2005,
    "lastRenovation": 2020,
    "fieldType": "Artificial Turf",
    "surfaceQuality": 62,
    "fanExperience": 43,
    "homeFieldAdvantage": 48,
    "noiseRating": 47,
    "clubSeats": 5598,
    "suites": 1202
  },
  {
    "stadiumId": "stadium_umass",
    "schoolId": "school_umass",
    "stadiumName": "UMass Stadium",
    "city": "Amherst",
    "state": "MA",
    "capacity": 78633,
    "currentCapacity": 78633,
    "targetCapacity": 78633,
    "yearBuilt": 1969,
    "lastRenovation": 2018,
    "fieldType": "Natural Grass",
    "surfaceQuality": 52,
    "fanExperience": 65,
    "homeFieldAdvantage": 88,
    "noiseRating": 49,
    "clubSeats": 3176,
    "suites": 655
  },
  {
    "stadiumId": "stadium_western_michigan",
    "schoolId": "school_western_michigan",
    "stadiumName": "Western Michigan Stadium",
    "city": "Kalamazoo",
    "state": "MI",
    "capacity": 58483,
    "currentCapacity": 58483,
    "targetCapacity": 58483,
    "yearBuilt": 1941,
    "lastRenovation": 2007,
    "fieldType": "Natural Grass",
    "surfaceQuality": 37,
    "fanExperience": 49,
    "homeFieldAdvantage": 39,
    "noiseRating": 56,
    "clubSeats": 2767,
    "suites": 1205
  },
  {
    "stadiumId": "stadium_sacramento_state",
    "schoolId": "school_sacramento_state",
    "stadiumName": "Sacramento State Stadium",
    "city": "Sacramento",
    "state": "CA",
    "capacity": 63248,
    "currentCapacity": 63248,
    "targetCapacity": 63248,
    "yearBuilt": 1958,
    "lastRenovation": 2006,
    "fieldType": "Artificial Turf",
    "surfaceQuality": 54,
    "fanExperience": 80,
    "homeFieldAdvantage": 77,
    "noiseRating": 70,
    "clubSeats": 2342,
    "suites": 1343
  },
  {
    "stadiumId": "stadium_air_force",
    "schoolId": "school_air_force",
    "stadiumName": "Air Force Stadium",
    "city": "USAF Academy",
    "state": "CO",
    "capacity": 80923,
    "currentCapacity": 80923,
    "targetCapacity": 80923,
    "yearBuilt": 1993,
    "lastRenovation": 2013,
    "fieldType": "Natural Grass",
    "surfaceQuality": 64,
    "fanExperience": 78,
    "homeFieldAdvantage": 80,
    "noiseRating": 61,
    "clubSeats": 3774,
    "suites": 1466
  },
  {
    "stadiumId": "stadium_hawaii",
    "schoolId": "school_hawaii",
    "stadiumName": "Hawaii Stadium",
    "city": "Honolulu",
    "state": "HI",
    "capacity": 70781,
    "currentCapacity": 70781,
    "targetCapacity": 70781,
    "yearBuilt": 1971,
    "lastRenovation": 2021,
    "fieldType": "Artificial Turf",
    "surfaceQuality": 53,
    "fanExperience": 37,
    "homeFieldAdvantage": 47,
    "noiseRating": 64,
    "clubSeats": 4594,
    "suites": 1583
  },
  {
    "stadiumId": "stadium_nevada",
    "schoolId": "school_nevada",
    "stadiumName": "Nevada Stadium",
    "city": "Reno",
    "state": "NV",
    "capacity": 68947,
    "currentCapacity": 68947,
    "targetCapacity": 68947,
    "yearBuilt": 1982,
    "lastRenovation": 2015,
    "fieldType": "Natural Grass",
    "surfaceQuality": 63,
    "fanExperience": 81,
    "homeFieldAdvantage": 70,
    "noiseRating": 66,
    "clubSeats": 5913,
    "suites": 562
  },
  {
    "stadiumId": "stadium_new_mexico",
    "schoolId": "school_new_mexico",
    "stadiumName": "New Mexico Stadium",
    "city": "Albuquerque",
    "state": "NM",
    "capacity": 69109,
    "currentCapacity": 69109,
    "targetCapacity": 69109,
    "yearBuilt": 2012,
    "lastRenovation": 2012,
    "fieldType": "Artificial Turf",
    "surfaceQuality": 43,
    "fanExperience": 36,
    "homeFieldAdvantage": 66,
    "noiseRating": 52,
    "clubSeats": 2623,
    "suites": 658
  },
  {
    "stadiumId": "stadium_san_jose_state",
    "schoolId": "school_san_jose_state",
    "stadiumName": "San Jose State Stadium",
    "city": "San Jose",
    "state": "CA",
    "capacity": 72883,
    "currentCapacity": 72883,
    "targetCapacity": 72883,
    "yearBuilt": 1937,
    "lastRenovation": 2025,
    "fieldType": "Natural Grass",
    "surfaceQuality": 55,
    "fanExperience": 73,
    "homeFieldAdvantage": 65,
    "noiseRating": 53,
    "clubSeats": 3722,
    "suites": 674
  },
  {
    "stadiumId": "stadium_unlv",
    "schoolId": "school_unlv",
    "stadiumName": "UNLV Stadium",
    "city": "Las Vegas",
    "state": "NV",
    "capacity": 58690,
    "currentCapacity": 58690,
    "targetCapacity": 58690,
    "yearBuilt": 1955,
    "lastRenovation": 2025,
    "fieldType": "Natural Grass",
    "surfaceQuality": 61,
    "fanExperience": 77,
    "homeFieldAdvantage": 59,
    "noiseRating": 51,
    "clubSeats": 5075,
    "suites": 324
  },
  {
    "stadiumId": "stadium_wyoming",
    "schoolId": "school_wyoming",
    "stadiumName": "Wyoming Stadium",
    "city": "Laramie",
    "state": "WY",
    "capacity": 90513,
    "currentCapacity": 90513,
    "targetCapacity": 90513,
    "yearBuilt": 1921,
    "lastRenovation": 2016,
    "fieldType": "Artificial Turf",
    "surfaceQuality": 74,
    "fanExperience": 81,
    "homeFieldAdvantage": 83,
    "noiseRating": 54,
    "clubSeats": 6424,
    "suites": 1833
  },
  {
    "stadiumId": "stadium_utep",
    "schoolId": "school_utep",
    "stadiumName": "UTEP Stadium",
    "city": "El Paso",
    "state": "TX",
    "capacity": 70874,
    "currentCapacity": 70874,
    "targetCapacity": 70874,
    "yearBuilt": 1988,
    "lastRenovation": 2024,
    "fieldType": "Natural Grass",
    "surfaceQuality": 61,
    "fanExperience": 72,
    "homeFieldAdvantage": 54,
    "noiseRating": 61,
    "clubSeats": 5562,
    "suites": 1114
  },
  {
    "stadiumId": "stadium_northern_illinois",
    "schoolId": "school_northern_illinois",
    "stadiumName": "Northern Illinois Stadium",
    "city": "DeKalb",
    "state": "IL",
    "capacity": 67874,
    "currentCapacity": 67874,
    "targetCapacity": 67874,
    "yearBuilt": 1921,
    "lastRenovation": 2010,
    "fieldType": "Artificial Turf",
    "surfaceQuality": 50,
    "fanExperience": 64,
    "homeFieldAdvantage": 46,
    "noiseRating": 54,
    "clubSeats": 2716,
    "suites": 511
  },
  {
    "stadiumId": "stadium_north_dakota_state",
    "schoolId": "school_north_dakota_state",
    "stadiumName": "North Dakota State Stadium",
    "city": "Fargo",
    "state": "ND",
    "capacity": 68328,
    "currentCapacity": 68328,
    "targetCapacity": 68328,
    "yearBuilt": 1983,
    "lastRenovation": 2023,
    "fieldType": "Natural Grass",
    "surfaceQuality": 69,
    "fanExperience": 81,
    "homeFieldAdvantage": 87,
    "noiseRating": 84,
    "clubSeats": 5013,
    "suites": 653
  },
  {
    "stadiumId": "stadium_boise_state",
    "schoolId": "school_boise_state",
    "stadiumName": "Boise State Stadium",
    "city": "Boise",
    "state": "ID",
    "capacity": 95024,
    "currentCapacity": 95024,
    "targetCapacity": 95024,
    "yearBuilt": 1929,
    "lastRenovation": 2023,
    "fieldType": "Artificial Turf",
    "surfaceQuality": 82,
    "fanExperience": 99,
    "homeFieldAdvantage": 98,
    "noiseRating": 95,
    "clubSeats": 5791,
    "suites": 562
  },
  {
    "stadiumId": "stadium_colorado_state",
    "schoolId": "school_colorado_state",
    "stadiumName": "Colorado State Stadium",
    "city": "Fort Collins",
    "state": "CO",
    "capacity": 73101,
    "currentCapacity": 73101,
    "targetCapacity": 73101,
    "yearBuilt": 1983,
    "lastRenovation": 2011,
    "fieldType": "Natural Grass",
    "surfaceQuality": 78,
    "fanExperience": 87,
    "homeFieldAdvantage": 79,
    "noiseRating": 66,
    "clubSeats": 4982,
    "suites": 1379
  },
  {
    "stadiumId": "stadium_fresno_state",
    "schoolId": "school_fresno_state",
    "stadiumName": "Fresno State Stadium",
    "city": "Fresno",
    "state": "CA",
    "capacity": 85499,
    "currentCapacity": 85499,
    "targetCapacity": 85499,
    "yearBuilt": 1986,
    "lastRenovation": 2018,
    "fieldType": "Artificial Turf",
    "surfaceQuality": 48,
    "fanExperience": 39,
    "homeFieldAdvantage": 63,
    "noiseRating": 45,
    "clubSeats": 5833,
    "suites": 1101
  },
  {
    "stadiumId": "stadium_oregon_state",
    "schoolId": "school_oregon_state",
    "stadiumName": "Oregon State Stadium",
    "city": "Corvallis",
    "state": "OR",
    "capacity": 70870,
    "currentCapacity": 70870,
    "targetCapacity": 70870,
    "yearBuilt": 1945,
    "lastRenovation": 2009,
    "fieldType": "Natural Grass",
    "surfaceQuality": 70,
    "fanExperience": 73,
    "homeFieldAdvantage": 55,
    "noiseRating": 70,
    "clubSeats": 4404,
    "suites": 1721
  },
  {
    "stadiumId": "stadium_san_diego_state",
    "schoolId": "school_san_diego_state",
    "stadiumName": "San Diego State Stadium",
    "city": "San Diego",
    "state": "CA",
    "capacity": 79563,
    "currentCapacity": 79563,
    "targetCapacity": 79563,
    "yearBuilt": 1926,
    "lastRenovation": 2026,
    "fieldType": "Artificial Turf",
    "surfaceQuality": 59,
    "fanExperience": 59,
    "homeFieldAdvantage": 98,
    "noiseRating": 74,
    "clubSeats": 4545,
    "suites": 1588
  },
  {
    "stadiumId": "stadium_texas_state",
    "schoolId": "school_texas_state",
    "stadiumName": "Texas State Stadium",
    "city": "San Marcos",
    "state": "TX",
    "capacity": 82974,
    "currentCapacity": 82974,
    "targetCapacity": 82974,
    "yearBuilt": 1945,
    "lastRenovation": 2025,
    "fieldType": "Artificial Turf",
    "surfaceQuality": 63,
    "fanExperience": 56,
    "homeFieldAdvantage": 74,
    "noiseRating": 42,
    "clubSeats": 3099,
    "suites": 1978
  },
  {
    "stadiumId": "stadium_utah_state",
    "schoolId": "school_utah_state",
    "stadiumName": "Utah State Stadium",
    "city": "Logan",
    "state": "UT",
    "capacity": 49965,
    "currentCapacity": 49965,
    "targetCapacity": 49965,
    "yearBuilt": 1981,
    "lastRenovation": 2006,
    "fieldType": "Natural Grass",
    "surfaceQuality": 58,
    "fanExperience": 57,
    "homeFieldAdvantage": 64,
    "noiseRating": 66,
    "clubSeats": 3075,
    "suites": 880
  },
  {
    "stadiumId": "stadium_washington_state",
    "schoolId": "school_washington_state",
    "stadiumName": "Washington State Stadium",
    "city": "Pullman",
    "state": "WA",
    "capacity": 76865,
    "currentCapacity": 76865,
    "targetCapacity": 76865,
    "yearBuilt": 1927,
    "lastRenovation": 2020,
    "fieldType": "Artificial Turf",
    "surfaceQuality": 74,
    "fanExperience": 23,
    "homeFieldAdvantage": 75,
    "noiseRating": 69,
    "clubSeats": 5335,
    "suites": 794
  },
  {
    "stadiumId": "stadium_appalachian_state",
    "schoolId": "school_appalachian_state",
    "stadiumName": "Appalachian State Stadium",
    "city": "Boone",
    "state": "NC",
    "capacity": 91466,
    "currentCapacity": 91466,
    "targetCapacity": 91466,
    "yearBuilt": 1992,
    "lastRenovation": 2011,
    "fieldType": "Artificial Turf",
    "surfaceQuality": 71,
    "fanExperience": 68,
    "homeFieldAdvantage": 73,
    "noiseRating": 79,
    "clubSeats": 6045,
    "suites": 493
  },
  {
    "stadiumId": "stadium_arkansas_state",
    "schoolId": "school_arkansas_state",
    "stadiumName": "Arkansas State Stadium",
    "city": "Jonesboro",
    "state": "AR",
    "capacity": 66959,
    "currentCapacity": 66959,
    "targetCapacity": 66959,
    "yearBuilt": 2010,
    "lastRenovation": 2026,
    "fieldType": "Artificial Turf",
    "surfaceQuality": 45,
    "fanExperience": 47,
    "homeFieldAdvantage": 39,
    "noiseRating": 85,
    "clubSeats": 4951,
    "suites": 919
  },
  {
    "stadiumId": "stadium_coastal_carolina",
    "schoolId": "school_coastal_carolina",
    "stadiumName": "Coastal Carolina Stadium",
    "city": "Conway",
    "state": "SC",
    "capacity": 65690,
    "currentCapacity": 65690,
    "targetCapacity": 65690,
    "yearBuilt": 1993,
    "lastRenovation": 2017,
    "fieldType": "Natural Grass",
    "surfaceQuality": 34,
    "fanExperience": 62,
    "homeFieldAdvantage": 68,
    "noiseRating": 64,
    "clubSeats": 4491,
    "suites": 465
  },
  {
    "stadiumId": "stadium_georgia_southern",
    "schoolId": "school_georgia_southern",
    "stadiumName": "Georgia Southern Stadium",
    "city": "Statesboro",
    "state": "GA",
    "capacity": 53033,
    "currentCapacity": 53033,
    "targetCapacity": 53033,
    "yearBuilt": 2008,
    "lastRenovation": 2007,
    "fieldType": "Artificial Turf",
    "surfaceQuality": 53,
    "fanExperience": 59,
    "homeFieldAdvantage": 65,
    "noiseRating": 53,
    "clubSeats": 3922,
    "suites": 1293
  },
  {
    "stadiumId": "stadium_georgia_state",
    "schoolId": "school_georgia_state",
    "stadiumName": "Georgia State Stadium",
    "city": "Atlanta",
    "state": "GA",
    "capacity": 64929,
    "currentCapacity": 64929,
    "targetCapacity": 64929,
    "yearBuilt": 1929,
    "lastRenovation": 2015,
    "fieldType": "Natural Grass",
    "surfaceQuality": 88,
    "fanExperience": 71,
    "homeFieldAdvantage": 61,
    "noiseRating": 94,
    "clubSeats": 5758,
    "suites": 763
  },
  {
    "stadiumId": "stadium_james_madison",
    "schoolId": "school_james_madison",
    "stadiumName": "James Madison Stadium",
    "city": "Harrisonburg",
    "state": "VA",
    "capacity": 98971,
    "currentCapacity": 98971,
    "targetCapacity": 98971,
    "yearBuilt": 1950,
    "lastRenovation": 2008,
    "fieldType": "Natural Grass",
    "surfaceQuality": 61,
    "fanExperience": 80,
    "homeFieldAdvantage": 67,
    "noiseRating": 71,
    "clubSeats": 2991,
    "suites": 668
  },
  {
    "stadiumId": "stadium_louisiana",
    "schoolId": "school_louisiana",
    "stadiumName": "Louisiana Stadium",
    "city": "Lafayette",
    "state": "LA",
    "capacity": 66208,
    "currentCapacity": 66208,
    "targetCapacity": 66208,
    "yearBuilt": 1968,
    "lastRenovation": 2016,
    "fieldType": "Natural Grass",
    "surfaceQuality": 70,
    "fanExperience": 55,
    "homeFieldAdvantage": 67,
    "noiseRating": 55,
    "clubSeats": 3053,
    "suites": 412
  },
  {
    "stadiumId": "stadium_louisiana_tech",
    "schoolId": "school_louisiana_tech",
    "stadiumName": "Louisiana Tech Stadium",
    "city": "Ruston",
    "state": "LA",
    "capacity": 74560,
    "currentCapacity": 74560,
    "targetCapacity": 74560,
    "yearBuilt": 1958,
    "lastRenovation": 2007,
    "fieldType": "Artificial Turf",
    "surfaceQuality": 75,
    "fanExperience": 51,
    "homeFieldAdvantage": 36,
    "noiseRating": 62,
    "clubSeats": 5817,
    "suites": 1383
  },
  {
    "stadiumId": "stadium_marshall",
    "schoolId": "school_marshall",
    "stadiumName": "Marshall Stadium",
    "city": "Huntington",
    "state": "WV",
    "capacity": 84793,
    "currentCapacity": 84793,
    "targetCapacity": 84793,
    "yearBuilt": 1928,
    "lastRenovation": 2007,
    "fieldType": "Artificial Turf",
    "surfaceQuality": 45,
    "fanExperience": 43,
    "homeFieldAdvantage": 52,
    "noiseRating": 67,
    "clubSeats": 7209,
    "suites": 444
  },
  {
    "stadiumId": "stadium_old_dominion",
    "schoolId": "school_old_dominion",
    "stadiumName": "Old Dominion Stadium",
    "city": "Norfolk",
    "state": "VA",
    "capacity": 48702,
    "currentCapacity": 48702,
    "targetCapacity": 48702,
    "yearBuilt": 1953,
    "lastRenovation": 2017,
    "fieldType": "Artificial Turf",
    "surfaceQuality": 50,
    "fanExperience": 54,
    "homeFieldAdvantage": 66,
    "noiseRating": 72,
    "clubSeats": 3267,
    "suites": 906
  },
  {
    "stadiumId": "stadium_south_alabama",
    "schoolId": "school_south_alabama",
    "stadiumName": "South Alabama Stadium",
    "city": "Mobile",
    "state": "AL",
    "capacity": 79169,
    "currentCapacity": 79169,
    "targetCapacity": 79169,
    "yearBuilt": 1976,
    "lastRenovation": 2015,
    "fieldType": "Artificial Turf",
    "surfaceQuality": 70,
    "fanExperience": 48,
    "homeFieldAdvantage": 34,
    "noiseRating": 62,
    "clubSeats": 6714,
    "suites": 1040
  },
  {
    "stadiumId": "stadium_southern_miss",
    "schoolId": "school_southern_miss",
    "stadiumName": "Southern Miss Stadium",
    "city": "Hattiesburg",
    "state": "MS",
    "capacity": 74041,
    "currentCapacity": 74041,
    "targetCapacity": 74041,
    "yearBuilt": 1927,
    "lastRenovation": 2012,
    "fieldType": "Natural Grass",
    "surfaceQuality": 31,
    "fanExperience": 60,
    "homeFieldAdvantage": 50,
    "noiseRating": 43,
    "clubSeats": 5879,
    "suites": 1118
  },
  {
    "stadiumId": "stadium_troy",
    "schoolId": "school_troy",
    "stadiumName": "Troy Stadium",
    "city": "Troy",
    "state": "AL",
    "capacity": 85397,
    "currentCapacity": 85397,
    "targetCapacity": 85397,
    "yearBuilt": 1947,
    "lastRenovation": 2012,
    "fieldType": "Natural Grass",
    "surfaceQuality": 64,
    "fanExperience": 54,
    "homeFieldAdvantage": 49,
    "noiseRating": 56,
    "clubSeats": 6560,
    "suites": 1737
  },
  {
    "stadiumId": "stadium_ulm",
    "schoolId": "school_ulm",
    "stadiumName": "ULM Stadium",
    "city": "Monroe",
    "state": "LA",
    "capacity": 40837,
    "currentCapacity": 40837,
    "targetCapacity": 40837,
    "yearBuilt": 1947,
    "lastRenovation": 2019,
    "fieldType": "Artificial Turf",
    "surfaceQuality": 30,
    "fanExperience": 18,
    "homeFieldAdvantage": 34,
    "noiseRating": 42,
    "clubSeats": 2478,
    "suites": 745
  },
  {
    "stadiumId": "stadium_notre_dame",
    "schoolId": "school_notre_dame",
    "stadiumName": "Notre Dame Stadium",
    "city": "South Bend",
    "state": "IN",
    "capacity": 98630,
    "currentCapacity": 98630,
    "targetCapacity": 98630,
    "yearBuilt": 1996,
    "lastRenovation": 2017,
    "fieldType": "Artificial Turf",
    "surfaceQuality": 76,
    "fanExperience": 85,
    "homeFieldAdvantage": 76,
    "noiseRating": 68,
    "clubSeats": 4494,
    "suites": 1318
  },
  {
    "stadiumId": "stadium_uconn",
    "schoolId": "school_uconn",
    "stadiumName": "UConn Stadium",
    "city": "Storrs",
    "state": "CT",
    "capacity": 51178,
    "currentCapacity": 51178,
    "targetCapacity": 51178,
    "yearBuilt": 1943,
    "lastRenovation": 2014,
    "fieldType": "Natural Grass",
    "surfaceQuality": 34,
    "fanExperience": 54,
    "homeFieldAdvantage": 48,
    "noiseRating": 34,
    "clubSeats": 4337,
    "suites": 1225
  }
]